pycerializer/__init__.py
pycerializer/pycerializer.py
pycerializer-0.5.7.dist-info/LICENSE
pycerializer-0.5.7.dist-info/METADATA
pycerializer-0.5.7.dist-info/WHEEL
pycerializer-0.5.7.dist-info/top_level.txt
pycerializer-0.5.7.dist-info/RECORD
